hygrapher/__init__.py
hygrapher/__main__.py
hygrapher/main.py
hygrapher/main_3d.py
hygrapher-0.5.1.dist-info/METADATA
hygrapher-0.5.1.dist-info/WHEEL
hygrapher-0.5.1.dist-info/entry_points.txt
hygrapher-0.5.1.dist-info/top_level.txt
hygrapher-0.5.1.dist-info/RECORD
